CASTING/MCTS.py
CASTING/__init__.py
CASTING/aseEamEvaluate.py
CASTING/clusterfun.py
CASTING/lammpsEvaluate.py
CASTING/perturb.py
CASTING/utilis.py
CASTING/writer.py
CASTING-0.1.4.data/scripts/MCTS.py
CASTING-0.1.4.data/scripts/clusterfun.py
CASTING-0.1.4.data/scripts/lammpsEvaluate.py
CASTING-0.1.4.data/scripts/perturb.py
CASTING-0.1.4.data/scripts/utilis.py
CASTING-0.1.4.dist-info/LICENSE
CASTING-0.1.4.dist-info/METADATA
CASTING-0.1.4.dist-info/WHEEL
CASTING-0.1.4.dist-info/top_level.txt
CASTING-0.1.4.dist-info/RECORD
