Metadata-Version: 2.1
Name: CASTING
Version: 0.1.4
Summary: A continuous action space tree search for inverse design (CASTING)
Home-page: https://github.com/sbanik2/CASTING
Author: Suvo Banik
Author-email: Suvo Banik <sbanik2@uic.edu>
Classifier: Programming Language :: Python :: 3
Classifier: License :: OSI Approved :: MIT License
Classifier: Operating System :: OS Independent
Requires-Python: >=3.9
License-File: LICENSE
Requires-Dist: numpy ==1.25.2
Requires-Dist: scipy ==1.11.2
Requires-Dist: pandas ==2.1.3
Requires-Dist: ase ==3.22.1
Requires-Dist: mendeleev ==0.13.1
Requires-Dist: networkx ==2.8.4
Requires-Dist: tqdm ==4.64.1
Requires-Dist: pymatgen ==2023.11.12
